amap_distance_matrix/__init__.py
amap_distance_matrix/helper.py
amap_distance_matrix/schemas/__init__.py
amap_distance_matrix/schemas/amap.py
amap_distance_matrix/schemas/dishashing.py
amap_distance_matrix/schemas/persistence.py
amap_distance_matrix/schemas/sqlalchemy_pydantic_orm.py
amap_distance_matrix/services/__init__.py
amap_distance_matrix/services/dishashing.py
amap_distance_matrix/services/geo.py
amap_distance_matrix/services/geohashing.py
amap_distance_matrix/services/navigation.py
amap_distance_matrix/services/osrm.py
amap_distance_matrix/services/persistence.py
amap_distance_matrix/services/register.py
amap_distance_matrix/services/service.py
amap_distance_matrix/services/smooth_weight.py
amap_distance_matrix-0.4.5.dist-info/LICENSE
amap_distance_matrix-0.4.5.dist-info/LICENSE.md
amap_distance_matrix-0.4.5.dist-info/WHEEL
amap_distance_matrix-0.4.5.dist-info/METADATA
amap_distance_matrix-0.4.5.dist-info/RECORD
